README.md
setup.py
IBLearning/__init__.py
IBLearning.egg-info/PKG-INFO
IBLearning.egg-info/SOURCES.txt
IBLearning.egg-info/dependency_links.txt
IBLearning.egg-info/requires.txt
IBLearning.egg-info/top_level.txt
IBLearning/MachineLearning/__init__.py
IBLearning/MachineLearning/KMeansCluster/__init__.py
IBLearning/MachineLearning/KMeansCluster/TextClustering/Cluster.py
IBLearning/MachineLearning/KMeansCluster/TextClustering/ClusterType.py
IBLearning/MachineLearning/KMeansCluster/TextClustering/PreProcessing.py
IBLearning/MachineLearning/KMeansCluster/TextClustering/TextClustering.py
IBLearning/MachineLearning/KMeansCluster/TextClustering/Word.py
IBLearning/MachineLearning/KMeansCluster/TextClustering/__init__.py