Metadata-Version: 2.1
Name: IBLearning
Version: 1.0.3
Summary: IBLearning is a Python module that contains a set of tools to help you to make your own machine learning algorithms.
Home-page: https://github.com/IB-Solution/IBLearning
Author: Alix Hamidou
Author-email: alix.hamidou@gmail.com
License: MIT
Classifier: Development Status :: 4 - Beta
Classifier: Intended Audience :: Developers
Classifier: License :: OSI Approved :: MIT License
Classifier: Operating System :: Microsoft :: Windows
Classifier: Operating System :: Unix
Classifier: Programming Language :: Python :: 3
Classifier: Topic :: Software Development :: Libraries :: Python Modules
Classifier: Topic :: Scientific/Engineering :: Artificial Intelligence
Classifier: Topic :: Scientific/Engineering :: Information Analysis
Classifier: Topic :: Text Processing :: Linguistic
